chimerapy/engine/__init__.py
chimerapy/engine/_debug.py
chimerapy/engine/_logger.py
chimerapy/engine/chimerapyrc.yaml
chimerapy/engine/config.py
chimerapy/engine/exceptions.py
chimerapy/engine/graph.py
chimerapy/engine/service.py
chimerapy/engine/states.py
chimerapy/engine/utils.py
chimerapy/engine/version.py
chimerapy/engine/entry/__init__.py
chimerapy/engine/entry/worker.py
chimerapy/engine/logger/__init__.py
chimerapy/engine/logger/common.py
chimerapy/engine/logger/distributed_logs_sink.py
chimerapy/engine/logger/utils.py
chimerapy/engine/logger/zmq_handlers.py
chimerapy/engine/manager/__init__.py
chimerapy/engine/manager/distributed_logging_service.py
chimerapy/engine/manager/http_server_service.py
chimerapy/engine/manager/manager.py
chimerapy/engine/manager/manager_service.py
chimerapy/engine/manager/manager_services_group.py
chimerapy/engine/manager/session_record_service.py
chimerapy/engine/manager/worker_handler_service.py
chimerapy/engine/manager/zeroconf_service.py
chimerapy/engine/networking/__init__.py
chimerapy/engine/networking/async_loop_thread.py
chimerapy/engine/networking/client.py
chimerapy/engine/networking/data_chunk.py
chimerapy/engine/networking/enums.py
chimerapy/engine/networking/publisher.py
chimerapy/engine/networking/server.py
chimerapy/engine/networking/subscriber.py
chimerapy/engine/node/__init__.py
chimerapy/engine/node/node.py
chimerapy/engine/node/node_config.py
chimerapy/engine/node/node_service.py
chimerapy/engine/node/poller_service.py
chimerapy/engine/node/processor_service.py
chimerapy/engine/node/publisher_service.py
chimerapy/engine/node/record_service.py
chimerapy/engine/node/registered_method.py
chimerapy/engine/node/worker_comms_service.py
chimerapy/engine/records/__init__.py
chimerapy/engine/records/audio_record.py
chimerapy/engine/records/image_record.py
chimerapy/engine/records/record.py
chimerapy/engine/records/tabular_record.py
chimerapy/engine/records/video_record.py
chimerapy/engine/worker/__init__.py
chimerapy_engine-0.1.0.dist-info/LICENSE.txt
chimerapy_engine-0.1.0.dist-info/METADATA
chimerapy_engine-0.1.0.dist-info/WHEEL
chimerapy_engine-0.1.0.dist-info/entry_points.txt
chimerapy_engine-0.1.0.dist-info/top_level.txt
chimerapy_engine-0.1.0.dist-info/RECORD
