Metadata-Version: 2.1
Name: chimerapy-engine
Version: 0.1.0
Summary: ChimeraPy-Engine: The Cluster Networking Engine for the ChimeraPy framework
Author-email: Eduardo Davalos <eduardo.davalos.anaya@vanderbilt.edu>, Umesh Timalsina <umesh.timalsina@vanderbilt.edu>
License: GNU GENERAL PUBLIC LICENSE
Project-URL: homepath, https://github.com/ChimeraPy/ChimeraPy-Engine
Project-URL: documentation, https://chimerapy-engine.readthedocs.io/en/latest/index.html
Project-URL: repository, https://github.com/ChimeraPy/ChimeraPy-Engine
Keywords: multimodal,data,distributed,streaming,real-time
Classifier: Programming Language :: Python :: 3
Requires-Python: >3.6
License-File: LICENSE.txt
Requires-Dist: networkx
Requires-Dist: dill
Requires-Dist: netifaces
Requires-Dist: matplotlib
Requires-Dist: multiprocess
Requires-Dist: opencv-python
Requires-Dist: pyaudio
Requires-Dist: pandas
Requires-Dist: tqdm
Requires-Dist: pyzmq
Requires-Dist: simplejpeg
Requires-Dist: aiohttp
Requires-Dist: blosc
Requires-Dist: PyYAML
Requires-Dist: dataclasses-json
Requires-Dist: aiofiles
Requires-Dist: zeroconf
Provides-Extra: benchmark
Requires-Dist: lz4 ; extra == 'benchmark'
Requires-Dist: nujson ; extra == 'benchmark'
Requires-Dist: orjson ; extra == 'benchmark'
Requires-Dist: cloudpickle ; extra == 'benchmark'
Requires-Dist: msgpack ; extra == 'benchmark'
Requires-Dist: msgpack-numpy ; extra == 'benchmark'
Provides-Extra: docs
Requires-Dist: sphinx ; extra == 'docs'
Requires-Dist: myst-parser ; extra == 'docs'
Provides-Extra: examples
Requires-Dist: imutils ; extra == 'examples'
Requires-Dist: numpy ; extra == 'examples'
Requires-Dist: pillow ; extra == 'examples'
Requires-Dist: dxcam ; (sys_platform == "win32") and extra == 'examples'
Provides-Extra: test
Requires-Dist: pytest ; extra == 'test'
Requires-Dist: pytest-asyncio ; extra == 'test'
Requires-Dist: pytest-repeat ; extra == 'test'
Requires-Dist: pytest-lazy-fixture ; extra == 'test'
Requires-Dist: pytest-order ; extra == 'test'
Requires-Dist: pytest-rerunfailures ; extra == 'test'
Requires-Dist: pytest-timeout ; extra == 'test'
Requires-Dist: auto-changelog ; extra == 'test'
Requires-Dist: coveralls ; extra == 'test'
Requires-Dist: pre-commit ; extra == 'test'
Requires-Dist: docker ; extra == 'test'
Requires-Dist: numpy ; extra == 'test'
Requires-Dist: imutils ; extra == 'test'
Requires-Dist: pillow ; extra == 'test'
Requires-Dist: requests ; extra == 'test'
Requires-Dist: bump2version ; extra == 'test'
